Workbook
Name TotalAssets: 资产负债表!B21
Name TotalLiabEquity: 资产负债表!E21

Sheet Sheet4

Sheet Sheet3

Sheet Sheet2

Sheet Sheet1

Sheet 辅助表
A1: 科目代码 | B1: 科目名称 | C1: 科目类型
A2: 1001 | B2: 库存现金 | C2: 资产
A3: 1002 | B3: 银行存款 | C3: 资产
A4: 1122 | B4: 应收账款 | C4: 资产
A5: 1401 | B5: 原材料 | C5: 资产
A6: 2001 | B6: 短期借款 | C6: 负债
A7: 2202 | B7: 应付账款 | C7: 负债
A8: 4001 | B8: 实收资本 | C8: 权益
A9: 5001 | B9: 主营业务收入 | C9: 收入
A10: 5101 | B10: 管理费用 | C10: 费用
A11: 5401 | B11: 销售费用 | C11: 费用

Sheet 明细账
A1: 45662 | B1: 1001 | C1: 库存现金 | D1: 资产 | E1: 50000 | F1: 0 | G1: 收到股东投资 | H1: VLOOKUP校验 | I1: 科目类型汇总
A2: 45662 | B2: 4001 | C2: 实收资本 | D2: 权益 | E2: 0 | F2: 50000 | G2: 收到股东投资 | H2: =IF(VLOOKUP(B2,辅助表!$A:$C,2,0)=C2,"OK","科目名不符") -> OK | I2: 科目类型 | J2: 借方合计 | K2: 贷方合计 | L2: 净额
A3: 45667 | B3: 1002 | C3: 银行存款 | D3: 资产 | E3: 200000 | F3: 0 | G3: 银行贷款到账 | H3: =IF(VLOOKUP(B3,辅助表!$A:$C,2,0)=C3,"OK","科目名不符") -> OK | I3: 资产 | J3: =SUMIF($D$2:$D$17,I3,$E$2:$E$17) -> 526000 | K3: =SUMIF($D$2:$D$17,I3,$F$2:$F$17) -> 105500 | L3: =J3-K3 -> 420500
A4: 45667 | B4: 2001 | C4: 短期借款 | D4: 负债 | E4: 0 | F4: 200000 | G4: 银行贷款到账 | H4: =IF(VLOOKUP(B4,辅助表!$A:$C,2,0)=C4,"OK","科目名不符") -> OK | I4: 负债 | J4: =SUMIF($D$2:$D$17,I4,$E$2:$E$17) -> 0 | K4: =SUMIF($D$2:$D$17,I4,$F$2:$F$17) -> 236000 | L4: =J4-K4 -> -236000
A5: 45672 | B5: 5001 | C5: 主营业务收入 | D5: 收入 | E5: 0 | F5: 85000 | G5: 销售产品A | H5: =IF(VLOOKUP(B5,辅助表!$A:$C,2,0)=C5,"OK","科目名不符") -> OK | I5: 权益 | J5: =SUMIF($D$2:$D$17,I5,$E$2:$E$17) -> 0 | K5: =SUMIF($D$2:$D$17,I5,$F$2:$F$17) -> 50000 | L5: =J5-K5 -> -50000
A6: 45672 | B6: 1122 | C6: 应收账款 | D6: 资产 | E6: 85000 | F6: 0 | G6: 销售产品A | H6: =IF(VLOOKUP(B6,辅助表!$A:$C,2,0)=C6,"OK","科目名不符") -> OK | I6: 收入 | J6: =SUMIF($D$2:$D$17,I6,$E$2:$E$17) -> 0 | K6: =SUMIF($D$2:$D$17,I6,$F$2:$F$17) -> 205000 | L6: =J6-K6 -> -205000
A7: 45677 | B7: 5401 | C7: 销售费用 | D7: 费用 | E7: 12000 | F7: 0 | G7: 支付销售佣金 | H7: =IF(VLOOKUP(B7,辅助表!$A:$C,2,0)=C7,"OK","科目名不符") -> OK | I7: 费用 | J7: =SUMIF($D$2:$D$17,I7,$E$2:$E$17) -> 20500 | K7: =SUMIF($D$2:$D$17,I7,$F$2:$F$17) -> 0 | L7: =J7-K7 -> 20500
A8: 45677 | B8: 1002 | C8: 银行存款 | D8: 资产 | E8: 0 | F8: 12000 | G8: 支付销售佣金 | H8: =IF(VLOOKUP(B8,辅助表!$A:$C,2,0)=C8,"OK","科目名不符") -> OK | I8: 合计 | J8: =SUM(J3:J7) -> 546500 | K8: =SUM(K3:K7) -> 596500 | L8: =SUM(L3:L7) -> -50000
A9: 45691 | B9: 1401 | C9: 原材料 | D9: 资产 | E9: 36000 | F9: 0 | G9: 采购原材料 | H9: =IF(VLOOKUP(B9,辅助表!$A:$C,2,0)=C9,"OK","科目名不符") -> OK
A10: 45691 | B10: 2202 | C10: 应付账款 | D10: 负债 | E10: 0 | F10: 36000 | G10: 采购原材料 | H10: =IF(VLOOKUP(B10,辅助表!$A:$C,2,0)=C10,"OK","科目名不符") -> OK
A11: 45698 | B11: 5101 | C11: 管理费用 | D11: 费用 | E11: 8500 | F11: 0 | G11: 支付办公费 | H11: =IF(VLOOKUP(B11,辅助表!$A:$C,2,0)=C11,"OK","科目名不符") -> OK
A12: 45698 | B12: 1002 | C12: 银行存款 | D12: 资产 | E12: 0 | F12: 8500 | G12: 支付办公费 | H12: =IF(VLOOKUP(B12,辅助表!$A:$C,2,0)=C12,"OK","科目名不符") -> OK
A13: 45706 | B13: 5001 | C13: 主营业务收入 | D13: 收入 | E13: 0 | F13: 120000 | G13: 销售产品B | H13: =IF(VLOOKUP(B13,辅助表!$A:$C,2,0)=C13,"OK","科目名不符") -> OK
A14: 45706 | B14: 1122 | C14: 应收账款 | D14: 资产 | E14: 120000 | F14: 0 | G14: 销售产品B | H14: =IF(VLOOKUP(B14,辅助表!$A:$C,2,0)=C14,"OK","科目名不符") -> OK
A15: 45717 | B15: 1002 | C15: 银行存款 | D15: 资产 | E15: 85000 | F15: 0 | G15: 收回应收账款 | H15: =IF(VLOOKUP(B15,辅助表!$A:$C,2,0)=C15,"OK","科目名不符") -> OK
A16: 45717 | B16: 1122 | C16: 应收账款 | D16: 资产 | E16: 0 | F16: 85000 | G16: 收回应收账款 | H16: =IF(VLOOKUP(B16,辅助表!$A:$C,2,0)=C16,"OK","科目名不符") -> OK
A17: 凭证日期 | B17: 科目代码 | C17: 科目名称 | D17: 科目类型 | E17: 借方金额 | F17: 贷方金额 | G17: 说明 | H17: =IF(VLOOKUP(B17,辅助表!$A:$C,2,0)=C17,"OK","科目名不符") -> OK

Sheet DCF模型
A1: 贷款摊还计划表 | H1: 项目DCF估值模型 (自由现金流)
A3: 贷款金额 | B3: 1000000 | H3: 折现率(WACC) | I3: 0.1
A4: 年利率 | B4: 0.045 | H4: 期初投资 | I4: -500000
A5: 期数(月) | B5: 60 | H5: 年份 | I5: 自由现金流
A6: 月还款额 | B6: =PMT(B4/12,B5,-B3) -> 18643.019 | H6: 1 | I6: 80000
H7: 2 | I7: 110000
A8: 期数 | B8: 期初余额 | C8: 月还款 | D8: 利息 | E8: 本金 | F8: 期末余额 | H8: 3 | I8: 150000
A9: 1 | B9: =$B$3 -> 1000000 | C9: =$B$6 -> 18643.019 | D9: =B9*$B$4/12 -> 3750 | E9: =C9-D9 -> 14893.019 | F9: =B9-E9 -> 985106.98 | H9: 4 | I9: 200000
A10: 2 | B10: =F9 -> 985106.98 | C10: =$B$6 -> 18643.019 | D10: =B10*$B$4/12 -> 3694.1512 | E10: =C10-D10 -> 14948.868 | F10: =B10-E10 -> 970158.11 | H10: 5 | I10: 280000
A11: 3 | B11: =F10 -> 970158.11 | C11: =$B$6 -> 18643.019 | D11: =B11*$B$4/12 -> 3638.0929 | E11: =C11-D11 -> 15004.926 | F11: =B11-E11 -> 955153.19
A12: 4 | B12: =F11 -> 955153.19 | C12: =$B$6 -> 18643.019 | D12: =B12*$B$4/12 -> 3581.8244 | E12: =C12-D12 -> 15061.195 | F12: =B12-E12 -> 940091.99 | H12: NPV | I12: =NPV(I3,I6:I10)+I4 -> 86794.245
A13: 5 | B13: =F12 -> 940091.99 | C13: =$B$6 -> 18643.019 | D13: =B13*$B$4/12 -> 3525.345 | E13: =C13-D13 -> 15117.674 | F13: =B13-E13 -> 924974.32 | H13: IRR | I13: =IRR(I4:I10) -> 0.15338761
A14: 6 | B14: =F13 -> 924974.32 | C14: =$B$6 -> 18643.019 | D14: =B14*$B$4/12 -> 3468.6537 | E14: =C14-D14 -> 15174.366 | F14: =B14-E14 -> 909799.95
A15: 7 | B15: =F14 -> 909799.95 | C15: =$B$6 -> 18643.019 | D15: =B15*$B$4/12 -> 3411.7498 | E15: =C15-D15 -> 15231.269 | F15: =B15-E15 -> 894568.68
A16: 8 | B16: =F15 -> 894568.68 | C16: =$B$6 -> 18643.019 | D16: =B16*$B$4/12 -> 3354.6326 | E16: =C16-D16 -> 15288.387 | F16: =B16-E16 -> 879280.3
A17: 9 | B17: =F16 -> 879280.3 | C17: =$B$6 -> 18643.019 | D17: =B17*$B$4/12 -> 3297.3011 | E17: =C17-D17 -> 15345.718 | F17: =B17-E17 -> 863934.58
A18: 10 | B18: =F17 -> 863934.58 | C18: =$B$6 -> 18643.019 | D18: =B18*$B$4/12 -> 3239.7547 | E18: =C18-D18 -> 15403.265 | F18: =B18-E18 -> 848531.31
A19: 11 | B19: =F18 -> 848531.31 | C19: =$B$6 -> 18643.019 | D19: =B19*$B$4/12 -> 3181.9924 | E19: =C19-D19 -> 15461.027 | F19: =B19-E19 -> 833070.29
A20: 12 | B20: =F19 -> 833070.29 | C20: =$B$6 -> 18643.019 | D20: =B20*$B$4/12 -> 3124.0136 | E20: =C20-D20 -> 15519.006 | F20: =B20-E20 -> 817551.28

Sheet 损益表
A1: 项目 | B1: 本期实际 | C1: 本期预算 | D1: 差异额 | E1: 差异率% | F1: 上期实际
A2: 一、营业收入 | B2: 5200000 | C2: 5000000 | D2: =IF(AND(B2<>"",C2<>""),B2-C2,"") -> 200000 | E2: =IF(AND(D2<>"",C2<>0),D2/C2,"") -> 0.04 | F2: 4800000
A3: 减：营业成本 | B3: 3120000 | C3: 3000000 | D3: =IF(AND(B3<>"",C3<>""),B3-C3,"") -> 120000 | E3: =IF(AND(D3<>"",C3<>0),D3/C3,"") -> 0.04 | F3: 2880000
A4: 二、毛利润 | B4: =B2-B3 -> 2080000 | C4: =C2-C3 -> 2000000 | D4: =IF(AND(B4<>"",C4<>""),B4-C4,"") -> 80000 | E4: =IF(AND(D4<>"",C4<>0),D4/C4,"") -> 0.04 | F4: =F2-F3 -> 1920000
A5: 毛利率% | B5: =IF(B2=0,0,B4/B2) -> 0.4 | C5: =IF(C2=0,0,C4/C2) -> 0.4 | D5: =IF(AND(B5<>"",C5<>""),B5-C5,"") -> 0 | E5: =IF(AND(D5<>"",C5<>0),D5/C5,"") -> 0 | F5: =IF(F2=0,0,F4/F2) -> 0.4
A6: 减：销售费用 | B6: 520000 | C6: 480000 | D6: =IF(AND(B6<>"",C6<>""),B6-C6,"") -> 40000 | E6: =IF(AND(D6<>"",C6<>0),D6/C6,"") -> 0.083333333 | F6: 450000
A7: 减：管理费用 | B7: 380000 | C7: 360000 | D7: =IF(AND(B7<>"",C7<>""),B7-C7,"") -> 20000 | E7: =IF(AND(D7<>"",C7<>0),D7/C7,"") -> 0.055555556 | F7: 340000
A8: 减：研发费用 | B8: 210000 | C8: 200000 | D8: =IF(AND(B8<>"",C8<>""),B8-C8,"") -> 10000 | E8: =IF(AND(D8<>"",C8<>0),D8/C8,"") -> 0.05 | F8: 180000
A9: 三、营业利润(EBIT) | B9: =B4-B6-B7-B8 -> 970000 | C9: =C4-C6-C7-C8 -> 960000 | D9: =IF(AND(B9<>"",C9<>""),B9-C9,"") -> 10000 | E9: =IF(AND(D9<>"",C9<>0),D9/C9,"") -> 0.010416667 | F9: =F4-F6-F7-F8 -> 950000
A10: 减：利息费用 | B10: 45000 | C10: 42000 | D10: =IF(AND(B10<>"",C10<>""),B10-C10,"") -> 3000 | E10: =IF(AND(D10<>"",C10<>0),D10/C10,"") -> 0.071428571 | F10: 40000
A11: 四、税前利润(EBT) | B11: =B9-B10 -> 925000 | C11: =C9-C10 -> 918000 | D11: =IF(AND(B11<>"",C11<>""),B11-C11,"") -> 7000 | E11: =IF(AND(D11<>"",C11<>0),D11/C11,"") -> 0.0076252723 | F11: =F9-F10 -> 910000
A12: 减：所得税(25%) | B12: =B11*0.25 -> 231250 | C12: =C11*0.25 -> 229500 | D12: =IF(AND(B12<>"",C12<>""),B12-C12,"") -> 1750 | E12: =IF(AND(D12<>"",C12<>0),D12/C12,"") -> 0.0076252723 | F12: =F11*0.25 -> 227500
A13: 五、净利润 | B13: =B11-B12 -> 693750 | C13: =C11-C12 -> 688500 | D13: =IF(AND(B13<>"",C13<>""),B13-C13,"") -> 5250 | E13: =IF(AND(D13<>"",C13<>0),D13/C13,"") -> 0.0076252723 | F13: =F11-F12 -> 682500
A14: 净利率% | B14: =IF(B2=0,0,B13/B2) -> 0.13341346 | C14: =IF(C2=0,0,C13/C2) -> 0.1377 | D14: =IF(AND(B14<>"",C14<>""),B14-C14,"") -> -0.0042865385 | E14: =IF(AND(D14<>"",C14<>0),D14/C14,"") -> -0.031129546

Sheet 资产负债表
A1: XX 科技有限公司 资产负债表 2025-12-31
A2: 资产 | B2: 期末余额 | C2: 期初余额 | D2: 负债及所有者权益 | E2: 期末余额 | F2: 期初余额
A3: 流动资产： | D3: 流动负债：
A4: 货币资金 | B4: 850000 | C4: 720000 | D4: 短期借款 | E4: 200000 | F4: 150000
A5: 应收账款 | B5: 430000 | C5: 380000 | D5: 应付账款 | E5: 310000 | F5: 270000
A6: 存货 | B6: 280000 | C6: 260000 | D6: 预收款项 | E6: 45000 | F6: 38000
A7: 预付账款 | B7: 35000 | C7: 28000 | D7: 应付职工薪酬 | E7: 82000 | F7: 76000
A8: 其他流动资产 | B8: 15000 | C8: 12000 | D8: 应交税费 | E8: 28000 | F8: 24000
A9: 流动资产合计 | B9: =SUM(B4:B8) -> 1610000 | C9: =SUM(C4:C8) -> 1400000 | D9: 流动负债合计 | E9: =SUM(E4:E8) -> 665000 | F9: =SUM(F4:F8) -> 558000
A11: 非流动资产： | D11: 非流动负债：
A12: 固定资产净值 | B12: 1200000 | C12: 1350000 | D12: 长期借款 | E12: 500000 | F12: 600000
A13: 无形资产 | B13: 180000 | C13: 200000 | D13: 长期应付款 | E13: 80000 | F13: 90000
A14: 长期投资 | B14: =SUM(B11:B13) -> 1380000 | C14: =SUM(C11:C13) -> 1550000 | E14: =SUM(E11:E12) -> 500000 | F14: =SUM(F11:F12) -> 600000
A15: 非流动资产合计 | D15: 非流动负债合计
D17: 所有者权益：
D18: 实收资本 | E18: 800000 | F18: 800000
D19: 资本公积 | E19: 200000 | F19: 200000
D20: 未分配利润 | E20: =SUM(E17:E19) -> 1000000 | F20: =SUM(F17:F19) -> 1000000
B21: =B9+B14 -> 2990000 | C21: =C9+C14 -> 2950000 | D21: 所有者权益合计 | E21: =E9+E14+E20 -> 2165000 | F21: =F9+F14+F20 -> 2158000
A22: 资产总计 | D22: 负债和所有者权益合计
A23: =IF(ABS(TotalAssets-TotalLiabEquity)<1,"OK - 借贷平衡","ERR - 借贷不平衡") -> OK - 借贷平衡

Sheet 上期比较
A1: XX 科技有限公司 资产负债表 2025-12-31
A2: 资产 | B2: 期末余额 | C2: 期初余额 | D2: 负债及所有者权益 | E2: 期末余额 | F2: 期初余额
A3: 流动资产： | D3: 流动负债：
A4: 货币资金 | B4: 850000 | C4: 720000 | D4: 短期借款 | E4: 200000 | F4: 150000
A5: 应收账款 | B5: 430000 | C5: 380000 | D5: 应付账款 | E5: 310000 | F5: 270000
A6: 存货 | B6: 280000 | C6: 260000 | D6: 预收款项 | E6: 45000 | F6: 38000
A7: 预付账款 | B7: 35000 | C7: 28000 | D7: 应付职工薪酬 | E7: 82000 | F7: 76000
A8: 其他流动资产 | B8: 15000 | C8: 12000 | D8: 应交税费 | E8: 28000 | F8: 24000
A9: 流动资产合计 | B9: =SUM(B4:B8) -> 1610000 | C9: =SUM(C4:C8) -> 1400000 | D9: 流动负债合计 | E9: =SUM(E4:E8) -> 665000 | F9: =SUM(F4:F8) -> 558000
A11: 非流动资产： | D11: 非流动负债：
A12: 固定资产净值 | B12: 1200000 | C12: 1350000 | D12: 长期借款 | E12: 500000 | F12: 600000
A13: 无形资产 | B13: 180000 | C13: 200000 | D13: 长期应付款 | E13: 80000 | F13: 90000
A14: 长期投资 | B14: =SUM(B11:B13) -> 1380000 | C14: =SUM(C11:C13) -> 1550000 | E14: =SUM(E11:E12) -> 500000 | F14: =SUM(F11:F12) -> 600000
A15: 非流动资产合计 | D15: 非流动负债合计
D17: 所有者权益：
D18: 实收资本 | E18: 800000 | F18: 800000
D19: 资本公积 | E19: 200000 | F19: 200000
D20: 未分配利润 | E20: =SUM(E17:E19) -> 1000000 | F20: =SUM(F17:F19) -> 1000000
B21: =B9+B14 -> 2990000 | C21: =C9+C14 -> 2950000 | D21: 所有者权益合计 | E21: =E9+E14+E20 -> 2165000 | F21: =F9+F14+F20 -> 2158000
A22: 资产总计 | D22: 负债和所有者权益合计
A23: =IF(ABS(TotalAssets-TotalLiabEquity)<1,"OK - 借贷平衡","ERR - 借贷不平衡") -> OK - 借贷平衡
